{
  "settings": {
    "migrated": 6,
    "iconPacksPath": ".obsidian/icons",
    "fontSize": 16,
    "emojiStyle": "twemoji",
    "iconColor": null,
    "recentlyUsedIcons": [
      "LiHome",
      "LiPaperclip",
      "LiBookTemplate",
      "LiKanbanSquare",
      "LiCheckCheck"
    ],
    "recentlyUsedIconsSize": 5,
    "rules": [],
    "extraMargin": {
      "top": 0,
      "right": 4,
      "bottom": 0,
      "left": 0
    },
    "iconInTabsEnabled": true,
    "iconInTitleEnabled": true,
    "iconInTitlePosition": "inline",
    "iconInFrontmatterEnabled": false,
    "iconInFrontmatterFieldName": "icon",
    "iconColorInFrontmatterFieldName": "iconColor",
    "iconsBackgroundCheckEnabled": false,
    "iconsInNotesEnabled": true,
    "iconsInLinksEnabled": true,
    "iconIdentifier": ":",
    "lucideIconPackType": "native",
    "debugMode": false,
    "useInternalPlugins": false
  },
  "01 - Projekty": "LiPenTool",
  "02 - Przestrzenie": "LiPackage",
  "03 - Zasoby": "LiBook",
  "04 - Permanentne": "LiAward",
  "05 - Tymczasowe": "LiPen",
  "06 - Dziennik": "LiCalendar",
  "07 - Archiwum": "LiArchive",
  "99 - Meta": "LiCommand",
  "06 - Dziennik/00 - Notatki": "LiNotebookText",
  "06 - Dziennik/01 - Zadania": "LiCheckCheck",
  "06 - Dziennik/99 - Tablica zadań.md": "LiKanbanSquare",
  "99 - Meta/00 - Szablony": "LiBookTemplate",
  "99 - Meta/01 - Załączniki": "LiPaperclip",
  "01 - Projekty/00 - HomeOnTour": "LiHome"
}